{
  "version": 1,
  "sequence": "22_assy_0_1_paper_000000_000199",
  "frame_index": 4,
  "status": "accepted",
  "objects": [
    {
      "class_id": 0,
      "polygon": [
        [
          781.0,
          317.0
        ],
        [
          525.0,
          272.0
        ],
        [
          486.0,
          273.0
        ],
        [
          202.0,
          585.0
        ],
        [
          181.0,
          617.0
        ],
        [
          409.0,
          719.0
        ],
        [
          580.0,
          719.0
        ],
        [
          750.0,
          388.0
        ]
      ],
      "bbox": [
        181.0,
        272.0,
        600.0,
        447.0
      ],
      "area": 160868,
      "source": "samurai_parallel"
    }
  ]
}