{
  "version": 1,
  "sequence": "22_assy_0_1_paper_000000_000199",
  "frame_index": 97,
  "status": "accepted",
  "objects": [
    {
      "class_id": 0,
      "polygon": [
        [
          220.0,
          251.0
        ],
        [
          212.0,
          248.0
        ],
        [
          0.0,
          238.0
        ],
        [
          0.0,
          682.0
        ],
        [
          17.0,
          656.0
        ],
        [
          136.0,
          413.0
        ],
        [
          195.0,
          305.0
        ]
      ],
      "bbox": [
        0.0,
        238.0,
        220.0,
        444.0
      ],
      "area": 50266,
      "source": "samurai_parallel"
    }
  ]
}